<?xml version="1.0" encoding="UTF-8"?>
<objects serializationModel="Studio.02.01.00">
	<object class="AudioFile" id="{9444c711-8c15-4576-be61-0a99c35a874e}">
		<property name="assetPath">
			<value>Aud_ConsoleTalk_2.wav</value>
		</property>
		<property name="frequencyInKHz">
			<value>44.0999985</value>
		</property>
		<property name="channelCount">
			<value>2</value>
		</property>
		<property name="length">
			<value>0.22873015873015873</value>
		</property>
		<relationship name="masterAssetFolder">
			<destination>{c02e9820-8f81-4706-ba4a-533dc1fc6f27}</destination>
		</relationship>
	</object>
</objects>
